Iran_cities_info/Iran_cities_info.py
Iran_cities_info/__init__.py
Iran_cities_info/check.py
Iran_cities_info/assets/iran_cities_en.json
Iran_cities_info-0.1.2.dist-info/METADATA
Iran_cities_info-0.1.2.dist-info/WHEEL
Iran_cities_info-0.1.2.dist-info/top_level.txt
Iran_cities_info-0.1.2.dist-info/RECORD
